{
  "credit": "Made with Blockbench",
  "parent": "block/block",
  "render_type": "translucent",
  "textures": {
    "particle": "fireflies:block/illumerin_block_bottom",
    "4": "fireflies:block/illumerin_block_bottom",
    "5": "fireflies:block/illumerin_block_side"
  },
  "elements": [
    {
      "from": [0, 0, 0],
      "to": [16, 16, 16],
      "faces": {
        "north": {"uv": [0, 0, 16, 16], "texture": "#4", "cullface": "north"},
        "east": {"uv": [0, 0, 16, 16], "texture": "#4", "cullface": "east"},
        "south": {"uv": [0, 0, 16, 16], "texture": "#4", "cullface": "south"},
        "west": {"uv": [0, 0, 16, 16], "texture": "#4", "cullface": "west"},
        "up": {"uv": [0, 0, 16, 16], "texture": "#4", "cullface": "up"},
        "down": {"uv": [0, 0, 16, 16], "texture": "#4", "cullface": "down"}
      }
    },
    {
      "from": [2, 2, 2],
      "to": [14, 14, 14],
      "shade": false,
      "faces": {
        "north": {"uv": [0, 0, 12, 12],"emissivity": 15,  "texture": "#5"},
        "east": {"uv": [0, 0, 12, 12], "emissivity": 15, "texture": "#5"},
        "south": {"uv": [0, 0, 12, 12],"emissivity": 15,  "texture": "#5"},
        "west": {"uv": [0, 0, 12, 12], "emissivity": 15, "texture": "#5"},
        "up": {"uv": [0, 0, 12, 12], "emissivity": 15, "texture": "#5"},
        "down": {"uv": [0, 0, 12, 12],"emissivity": 15,  "texture": "#5"}
      }
    }
  ],
  "display": {}
}